elabftw_ude_cli/__init__.py
elabftw_ude_cli/api.py
elabftw_ude_cli/auto_update.py
elabftw_ude_cli/cli.py
elabftw_ude_cli/config.py
elabftw_ude_cli/create_modify.py
elabftw_ude_cli/file_actions.py
elabftw_ude_cli/read.py
elabftw_ude_cli/search.py
elabftw_ude_cli/visibility.py
elabftw_ude_cli-0.1.16.dist-info/licenses/LICENSE
elabftw_ude_cli-0.1.16.dist-info/METADATA
elabftw_ude_cli-0.1.16.dist-info/WHEEL
elabftw_ude_cli-0.1.16.dist-info/entry_points.txt
elabftw_ude_cli-0.1.16.dist-info/top_level.txt
elabftw_ude_cli-0.1.16.dist-info/RECORD
