Metadata-Version: 2.4
Name: elabftw_ude_cli
Version: 0.1.16
Summary: CLI wrapper for interacting with eLabFTW API at University of Duisburg-Essen
Author: Manan B Shah
Author-email: manan.shah@uni-due.de
Classifier: Programming Language :: Python :: 3
Classifier: License :: OSI Approved :: MIT License
Classifier: Operating System :: OS Independent
Requires-Python: >=3.7
License-File: LICENSE
Requires-Dist: requests
Requires-Dist: argcomplete
Requires-Dist: chardet
Dynamic: author
Dynamic: author-email
Dynamic: classifier
Dynamic: description
Dynamic: description-content-type
Dynamic: license-file
Dynamic: requires-dist
Dynamic: requires-python
Dynamic: summary
